procsimulator/CommunityGenerator.py
procsimulator/CommunityManager.py
procsimulator/CommunityManagerStrategy.py
procsimulator/CommunitySpecificator.py
procsimulator/ConsumptionGenerator.py
procsimulator/DataAcquisition.py
procsimulator/DataFromAPI.py
procsimulator/DataFromCSV.py
procsimulator/DataFromModel.py
procsimulator/DataFromSmile.py
procsimulator/DataFromTomorrow.py
procsimulator/Evaluation.py
procsimulator/Input.py
procsimulator/Knapsack.py
procsimulator/KnapsackBalancing.py
procsimulator/MinimizeCostsPyomo.py
procsimulator/RenewableEnergyGenerator.py
procsimulator/__init__.py
procsimulator/database/baseload.csv
procsimulator/database/database.conf
procsimulator/database/inverters.csv
procsimulator/database/timeslotsdatabase.csv
procsimulator/database/user1/AMPLIFIER.csv
procsimulator/database/user1/BREADCUTTER.csv
procsimulator/database/user1/CDPLAYER.csv
procsimulator/database/user1/COFFEEMAKER.csv
procsimulator/database/user1/COOKINGSTOVE.csv
procsimulator/database/user1/DISHWASHER.csv
procsimulator/database/user1/DRYER.csv
procsimulator/database/user1/FREEZER.csv
procsimulator/database/user1/IRON.csv
procsimulator/database/user1/KETTLE.csv
procsimulator/database/user1/MICROWAVE.csv
procsimulator/database/user1/Mary.csv
procsimulator/database/user1/PC.csv
procsimulator/database/user1/PRINTER.csv
procsimulator/database/user1/REFRIGERATOR.csv
procsimulator/database/user1/TOASTER.csv
procsimulator/database/user1/TV.csv
procsimulator/database/user1/VACUUMCLEANER.csv
procsimulator/database/user1/WASHINGMACHINE.csv
procsimulator/database/user1/baseload.csv
procsimulator/database/user1/dishwasher_operation.csv
procsimulator/database/user1/events.csv
procsimulator/database/user1/fridge_operation.csv
procsimulator/database/user1/total.csv
procsimulator/database/user1/use_a_personal_computer.csv
procsimulator/database/user1/vacuuming.csv
procsimulator/database/user1/washing_a_load_of_laundry.csv
procsimulator/database/user1/watching_TV.csv
procsimulator-0.1.2.dist-info/METADATA
procsimulator-0.1.2.dist-info/WHEEL
procsimulator-0.1.2.dist-info/licenses/LICENSE
procsimulator-0.1.2.dist-info/RECORD
