Metadata-Version: 2.1
Name: procsimulator
Version: 0.1.2
Summary: An energy community simulator to develop and evaluate load balancing schemes.
Project-URL: Homepage, https://gitlab.com/nunovelosa/procsim
Project-URL: Bug Tracker, https://gitlab.com/nunovelosa/procsim/issues
Author-email: Nuno Velosa <nunovelosa@hotmail.com>
License-File: LICENSE
Classifier: License :: OSI Approved :: MIT License
Classifier: Operating System :: OS Independent
Classifier: Programming Language :: Python :: 3
Requires-Python: >=3.7
